auto_deep_learning/__init__.py
auto_deep_learning/api/__init__.py
auto_deep_learning/api/main.py
auto_deep_learning/api/api_adl/__init__.py
auto_deep_learning/api/api_adl/config.py
auto_deep_learning/api/api_adl/crud/__init__.py
auto_deep_learning/api/api_adl/crud/base.py
auto_deep_learning/cloud/__init__.py
auto_deep_learning/cloud/aws/__init__.py
auto_deep_learning/cloud/gcp/__init__.py
auto_deep_learning/enum/__init__.py
auto_deep_learning/enum/model.py
auto_deep_learning/exceptions/__init__.py
auto_deep_learning/exceptions/model/__init__.py
auto_deep_learning/exceptions/model/definition.py
auto_deep_learning/exceptions/utils/__init__.py
auto_deep_learning/exceptions/utils/functions.py
auto_deep_learning/exceptions/utils/data_handler/__init__.py
auto_deep_learning/exceptions/utils/data_handler/img.py
auto_deep_learning/exceptions/utils/data_handler/loader.py
auto_deep_learning/model/__init__.py
auto_deep_learning/model/creation.py
auto_deep_learning/model/definition.py
auto_deep_learning/model/inference.py
auto_deep_learning/model/visualization.py
auto_deep_learning/model/arch/__init__.py
auto_deep_learning/model/arch/linear.py
auto_deep_learning/model/arch/transfer.py
auto_deep_learning/model/arch/convolution/__init__.py
auto_deep_learning/model/arch/convolution/simple.py
auto_deep_learning/schemas/__init__.py
auto_deep_learning/schemas/model.py
auto_deep_learning/utils/__init__.py
auto_deep_learning/utils/config.py
auto_deep_learning/utils/functions.py
auto_deep_learning/utils/singleton.py
auto_deep_learning/utils/data_handler/__init__.py
auto_deep_learning/utils/data_handler/loader.py
auto_deep_learning/utils/data_handler/creator/__init__.py
auto_deep_learning/utils/data_handler/creator/base_creator.py
auto_deep_learning/utils/data_handler/creator/data_creator.py
auto_deep_learning/utils/data_handler/transform/__init__.py
auto_deep_learning/utils/data_handler/transform/augmentation.py
auto_deep_learning/utils/data_handler/transform/constants.py
auto_deep_learning-0.1.5.4.dist-info/LICENSE.txt
auto_deep_learning-0.1.5.4.dist-info/METADATA
auto_deep_learning-0.1.5.4.dist-info/WHEEL
auto_deep_learning-0.1.5.4.dist-info/top_level.txt
auto_deep_learning-0.1.5.4.dist-info/RECORD
