Metadata-Version: 2.1
Name: auto-deep-learning
Version: 0.1.5.4
Summary: Automation of the creation of the architecture of the neural network based on the input
Home-page: https://github.com/Nil-Andreu/auto-deep-learning
Author: Nil Andreu
Author-email: nilandreug@email.com
License: MIT
Keywords: deep learning,machine learning,computer vision,convolutional neural networks,neural networks,image classification
Platform: UNKNOWN
Classifier: Development Status :: 3 - Alpha
Classifier: Intended Audience :: Developers
Classifier: Topic :: Software Development :: Build Tools
Classifier: License :: OSI Approved :: MIT License
Classifier: Programming Language :: Python :: 3.7
Classifier: Programming Language :: Python :: 3.8
Classifier: Programming Language :: Python :: 3.9
Classifier: Programming Language :: Python :: 3.10
License-File: LICENSE.txt
Requires-Dist: pandas (==1.5.0)
Requires-Dist: pre-commit (==2.21.0)
Requires-Dist: pytest
Requires-Dist: sentence-transformers (==2.2.2)
Requires-Dist: torch (==1.13.1)
Requires-Dist: torchaudio (==0.13.1)
Requires-Dist: torchsummary (==1.5.1)
Requires-Dist: torchvision (==0.14.1)
Requires-Dist: transformers (==4.25.1)
Provides-Extra: api
Requires-Dist: alembic ; extra == 'api'
Requires-Dist: fastapi ; extra == 'api'
Provides-Extra: cloud
Requires-Dist: pytest ; extra == 'cloud'
